plaque_size_tool.py
plaque_size_tool-1.0.8.dist-info/LICENSE
plaque_size_tool-1.0.8.dist-info/METADATA
plaque_size_tool-1.0.8.dist-info/WHEEL
plaque_size_tool-1.0.8.dist-info/top_level.txt
plaque_size_tool-1.0.8.dist-info/RECORD
