Metadata-Version: 2.1
Name: plaque-size-tool
Version: 1.0.8
Summary: Bacteriophage plaque size measurement tool
Home-page: http://github.com/ellinium/plaque_size_tool
Author: Ellina Trofimova, Ilya Trofimov
Author-email: ellina.trofimova@gmail.com
License: Apache 2.0
Keywords: bacteriophage phage virus viral plaque size
Platform: UNKNOWN
Requires-Dist: numpy
Requires-Dist: opencv-python
Requires-Dist: imutils
Requires-Dist: pandas
Requires-Dist: Pillow
